emerge/__init__.py
emerge/__main__.py
emerge/cli.py
emerge/core.py
emerge/ext.py
emerge/plot.py
emerge/read.py
emerge/write.py
emerge/_emerge/__init__.py
emerge/_emerge/bc.py
emerge/_emerge/cacherun.py
emerge/_emerge/cleanup.py
emerge/_emerge/const.py
emerge/_emerge/coord.py
emerge/_emerge/cs.py
emerge/_emerge/dataset.py
emerge/_emerge/emerge_update.py
emerge/_emerge/file.py
emerge/_emerge/geometry.py
emerge/_emerge/howto.py
emerge/_emerge/install_check.py
emerge/_emerge/logsettings.py
emerge/_emerge/mesh3d.py
emerge/_emerge/mesher.py
emerge/_emerge/optim.py
emerge/_emerge/periodic.py
emerge/_emerge/selection.py
emerge/_emerge/settings.py
emerge/_emerge/simmodel.py
emerge/_emerge/simstate.py
emerge/_emerge/simulation_data.py
emerge/_emerge/solver.py
emerge/_emerge/system.py
emerge/_emerge/backend/__init__.py
emerge/_emerge/backend/datasets.py
emerge/_emerge/elements/__init__.py
emerge/_emerge/elements/femdata.py
emerge/_emerge/elements/index_interp.py
emerge/_emerge/elements/ned2_interp.py
emerge/_emerge/elements/nedelec2.py
emerge/_emerge/elements/nedleg2.py
emerge/_emerge/geo/__init__.py
emerge/_emerge/geo/horn.py
emerge/_emerge/geo/modeler.py
emerge/_emerge/geo/open_region.py
emerge/_emerge/geo/operations.py
emerge/_emerge/geo/pcb.py
emerge/_emerge/geo/pmlbox.py
emerge/_emerge/geo/polybased.py
emerge/_emerge/geo/shapes.py
emerge/_emerge/geo/step.py
emerge/_emerge/geo/pcb_tools/calculator.py
emerge/_emerge/geo/pcb_tools/dxf.py
emerge/_emerge/geo/pcb_tools/macro.py
emerge/_emerge/mth/_cache_check.py
emerge/_emerge/mth/common_functions.py
emerge/_emerge/mth/integrals.py
emerge/_emerge/mth/loopsplit.py
emerge/_emerge/mth/optimized.py
emerge/_emerge/mth/pairing.py
emerge/_emerge/physics/__init__.py
emerge/_emerge/physics/microwave/__init__.py
emerge/_emerge/physics/microwave/adaptive_freq.py
emerge/_emerge/physics/microwave/adaptive_mesh.py
emerge/_emerge/physics/microwave/microwave_3d.py
emerge/_emerge/physics/microwave/microwave_bc.py
emerge-2.2.1.dist-info/METADATA
emerge-2.2.1.dist-info/WHEEL
emerge-2.2.1.dist-info/entry_points.txt
emerge-2.2.1.dist-info/licenses/LICENSE
emerge-2.2.1.dist-info/RECORD
