Metadata-Version: 2.4
Name: emerge
Version: 2.2.1
Summary: An open source EM FEM simulator in Python
Project-URL: Homepage, https://github.com/FennisRobert/EMerge
Project-URL: Issues, https://github.com/FennisRobert/EMerge/issues
License-File: LICENSE
Requires-Python: <4.0,>=3.10
Requires-Dist: emsutil>=0.4.0
Requires-Dist: gmsh<4.14.0,>=4.13.0
Requires-Dist: joblib>=1.5.1
Requires-Dist: loguru>=0.7.3
Requires-Dist: matplotlib>=3.8.0
Requires-Dist: mkl!=2024.0; platform_machine == 'x86_64' or platform_machine == 'AMD64'
Requires-Dist: msgpack-numpy>=0.4.8
Requires-Dist: msgpack>=1.1.2
Requires-Dist: numba<0.61.0,>=0.60.0; platform_system == 'Linux'
Requires-Dist: numba>=0.61; platform_system != 'Linux'
Requires-Dist: numpy<2.3,>=2.0; platform_system == 'Linux'
Requires-Dist: numpy<2.3,>=2.2; platform_system != 'Linux'
Requires-Dist: pyvista>=0.45.2
Requires-Dist: scipy>=1.14.0
Provides-Extra: cudss
Requires-Dist: cupy-cuda12x; extra == 'cudss'
Requires-Dist: nvidia-cudss-cu12==0.5.0.16; extra == 'cudss'
Requires-Dist: nvmath-python[cu12]==0.5.0; extra == 'cudss'
Provides-Extra: cudss12
Requires-Dist: cupy-cuda12x; extra == 'cudss12'
Requires-Dist: nvidia-cudss-cu12==0.5.0.16; extra == 'cudss12'
Requires-Dist: nvmath-python[cu12]==0.5.0; extra == 'cudss12'
Provides-Extra: dxf
Requires-Dist: ezdxf; extra == 'dxf'
Provides-Extra: gerber
Requires-Dist: pygerber; extra == 'gerber'
Provides-Extra: umfpack
Requires-Dist: scikit-umfpack; (sys_platform != 'win32') and extra == 'umfpack'
